{"assets":{"4537065B378A5C462E190492E9BAA329":{"type":"texture","index":6,"assetRequest":{"type":"slide","state":"outgoing","slide":"1706472B-602A-44A9-A0E8-069F3BD93CE1"},"url":{"web":"assets/4537065B378A5C462E190492E9BAA329.svg"},"width":1024,"height":768},"C068BAB1EF1EF519777AEAE0CC136B6C":{"type":"texture","index":7,"assetRequest":{"type":"slide","state":"incoming","slide":"AE36482B-602A-44A9-A0E8-069F3BD93CE1"},"url":{"web":"assets/C068BAB1EF1EF519777AEAE0CC136B6C.svg"},"width":1024,"height":768}},"events":[{"effects":[{"beginTime":0,"baseLayer":{"animations":[],"initialState":{"affineTransform":[1,0,0,1,0,0],"masksToBounds":false,"rotation":0,"scale":1,"position":{"pointX":512,"pointY":384},"width":1024,"sublayerTransform":[1,0,0,0,0,1,0,0,0,0,1,0,0,0,0,1],"contentsRect":{"y":0,"x":0,"width":1,"height":1},"opacity":1,"edgeAntialiasingMask":251658240,"height":768,"hidden":false,"anchorPoint":{"pointX":0.5,"pointY":0.5}},"objectID":"0","layers":[{"animations":[],"initialState":{"affineTransform":[1,0,0,1,0,0],"masksToBounds":false,"rotation":0,"scale":1,"position":{"pointX":512,"pointY":384},"width":1024,"sublayerTransform":[1,0,0,0,0,1,0,0,0,0,1,-0.0004922987690640373,0,0,0,1],"contentsRect":{"y":0,"x":0,"width":1,"height":1},"opacity":1,"edgeAntialiasingMask":251658240,"height":768,"hidden":false,"anchorPoint":{"pointX":0.5,"pointY":0.5}},"layers":[{"animations":[],"layers":[],"initialState":{"affineTransform":[1,0,0,1,0,0],"masksToBounds":false,"rotation":0,"scale":1,"position":{"pointX":512,"pointY":384},"width":1024,"sublayerTransform":[1,0,0,0,0,1,0,0,0,0,1,0,0,0,0,1],"contentsRect":{"y":0,"x":0,"width":1,"height":1},"opacity":1,"edgeAntialiasingMask":0,"height":768,"hidden":false,"anchorPoint":{"pointX":0.5,"pointY":0.5}},"texture":"C068BAB1EF1EF519777AEAE0CC136B6C"},{"animations":[{"timeOffset":0,"from":{"scalar":false},"beginTime":0,"repeatCount":0,"fillMode":"both","property":"hidden","autoreverses":false,"duration":0.01,"to":{"scalar":true}}],"layers":[],"initialState":{"affineTransform":[1,0,0,1,0,0],"masksToBounds":false,"rotation":0,"scale":1,"position":{"pointX":512,"pointY":384},"width":1024,"sublayerTransform":[1,0,0,0,0,1,0,0,0,0,1,0,0,0,0,1],"contentsRect":{"y":0,"x":0,"width":1,"height":1},"opacity":1,"edgeAntialiasingMask":0,"height":768,"hidden":false,"anchorPoint":{"pointX":0.5,"pointY":0.5}},"texture":"4537065B378A5C462E190492E9BAA329"}]}]},"effects":[],"duration":0.01,"type":"transition","name":"none","objectID":"0"}],"automaticPlay":false,"hyperlinks":[],"accessibility":[{"text":"￼","targetRectangle":{"y":732.5,"x":506.4959999024868,"width":10.00800000000004,"height":22}},{"text":"Web protocols (HTTP2)","targetRectangle":{"y":248.5707397460938,"x":121.5214419257641,"width":299.9409099999999,"height":35}},{"text":"Security and privacy (RFC7258, UTA, TLS1.3)","targetRectangle":{"y":283.5707397460938,"x":121.5214419257641,"width":417.88905,"height":88.06000030040741}},{"text":"Enabling real-time communications from browsers (WebRTC)","targetRectangle":{"y":371.6307400465012,"x":121.5214419257641,"width":460.55666,"height":88.06000030040741}},{"text":"Management, orchestration, virtualisation, and data-model driven networking (NVO, SFC, YANG)","targetRectangle":{"y":459.6907403469086,"x":121.5214419257641,"width":477.6121799999999,"height":123.0600003004074}},{"text":"Internet of Things","targetRectangle":{"y":582.750740647316,"x":121.5214419257641,"width":224.718,"height":53.06000030040741}},{"text":"Running code and open source","targetRectangle":{"y":635.8107409477234,"x":121.5214419257641,"width":407.8343599999998,"height":53.06000030040741}},{"text":"pasted-image.pdf","targetRectangle":{"y":53.90904998779297,"x":814.8624877929688,"width":188.1666870117188,"height":101.0524826049805}},{"text":"16857538896_429d028f0a_k.jpg","targetRectangle":{"y":216.3913726806641,"x":666.7805786132812,"width":336.8235473632812,"height":505.3587341308594}},{"text":"Some Recent","targetRectangle":{"y":24.4352912902832,"x":91.33333587646484,"width":403.4016000000001,"height":80}},{"text":"Areas of Work","targetRectangle":{"y":104.4352912902832,"x":91.33333587646484,"width":419.5968,"height":80}}],"baseLayer":{"animations":[],"initialState":{"affineTransform":[1,0,0,1,0,0],"masksToBounds":false,"rotation":0,"scale":1,"position":{"pointX":512,"pointY":384},"width":1024,"sublayerTransform":[1,0,0,0,0,1,0,0,0,0,1,0,0,0,0,1],"contentsRect":{"y":0,"x":0,"width":1,"height":1},"opacity":1,"edgeAntialiasingMask":251658240,"height":768,"hidden":false,"anchorPoint":{"pointX":0.5,"pointY":0.5}},"objectID":"0","layers":[{"animations":[],"initialState":{"affineTransform":[1,0,0,1,0,0],"masksToBounds":false,"rotation":0,"scale":1,"position":{"pointX":512,"pointY":384},"width":1024,"sublayerTransform":[1,0,0,0,0,1,0,0,0,0,1,-0.0004922987690640373,0,0,0,1],"contentsRect":{"y":0,"x":0,"width":1,"height":1},"opacity":1,"edgeAntialiasingMask":251658240,"height":768,"hidden":false,"anchorPoint":{"pointX":0.5,"pointY":0.5}},"layers":[{"animations":[],"layers":[],"initialState":{"affineTransform":[1,0,0,1,0,0],"masksToBounds":false,"rotation":0,"scale":1,"position":{"pointX":512,"pointY":384},"width":1024,"sublayerTransform":[1,0,0,0,0,1,0,0,0,0,1,0,0,0,0,1],"contentsRect":{"y":0,"x":0,"width":1,"height":1},"opacity":1,"edgeAntialiasingMask":0,"height":768,"hidden":false,"anchorPoint":{"pointX":0.5,"pointY":0.5}},"texture":"4537065B378A5C462E190492E9BAA329"}]}]}}]}